{
  "firstLayout": "",
  "gdVersion": {
    "build": 99,
    "major": 4,
    "minor": 0,
    "revision": 0
  },
  "properties": {
    "adaptGameResolutionAtRuntime": true,
    "folderProject": true,
    "orientation": "default",
    "packageName": "org.eu.awesomekalin",
    "pixelsRounding": false,
    "projectUuid": "e674182a-ba61-4ae1-8492-6e33d5b6d619",
    "scaleMode": "linear",
    "sizeOnStartupMode": "adaptWidth",
    "templateSlug": "",
    "useExternalSourceFiles": false,
    "version": "1.0.0",
    "name": "The Second War",
    "description": "",
    "author": "AwesomeKalin55",
    "windowWidth": 1920,
    "windowHeight": 1080,
    "latestCompilationDirectory": "",
    "maxFPS": 0,
    "minFPS": 20,
    "verticalSync": false,
    "platformSpecificAssets": {},
    "loadingScreen": {
      "backgroundColor": 0,
      "backgroundFadeInDuration": 0.2,
      "backgroundImageResourceName": "",
      "gdevelopLogoStyle": "light",
      "logoAndProgressFadeInDuration": 0.2,
      "logoAndProgressLogoFadeInDelay": 0.2,
      "minDuration": 1.5,
      "progressBarColor": 16777215,
      "progressBarHeight": 20,
      "progressBarMaxWidth": 200,
      "progressBarMinWidth": 40,
      "progressBarWidthPercent": 30,
      "showGDevelopSplash": true,
      "showProgressBar": true
    },
    "watermark": {
      "placement": "bottom-left",
      "showWatermark": false
    },
    "authorIds": [
      "Vu2ZkG9HyRchkjTdpXr4E3Fux7Q2"
    ],
    "authorUsernames": [
      "AwesomeKalin55"
    ],
    "categories": [],
    "playableDevices": [],
    "extensionProperties": [],
    "platforms": [
      {
        "name": "GDevelop JS platform"
      }
    ],
    "currentPlatform": "GDevelop JS platform"
  },
  "resources": {
    "resources": [
      {
        "alwaysLoaded": false,
        "file": "images/main-menu/Default_A_desolate_abandoned_farmstead_in_the_aftermath_of_a_0_36fbc916-2b00-4038-8c2f-b5c87d8455a2_1.jpg",
        "kind": "image",
        "metadata": "",
        "name": "images\\main-menu\\Default_A_desolate_abandoned_farmstead_in_the_aftermath_of_a_0_36fbc916-2b00-4038-8c2f-b5c87d8455a2_1.jpg",
        "smoothed": true,
        "userAdded": false
      }
    ],
    "resourceFolders": []
  },
  "objects": [],
  "objectsGroups": [],
  "variables": [],
  "layouts": [
    {
      "__REFERENCE_TO_SPLIT_OBJECT": true,
      "referenceTo": "/layouts/main-menu"
    }
  ],
  "externalEvents": [],
  "eventsFunctionsExtensions": [
    {
      "__REFERENCE_TO_SPLIT_OBJECT": true,
      "referenceTo": "/eventsFunctionsExtensions/withthreejs"
    }
  ],
  "externalLayouts": [],
  "externalSourceFiles": []
}